eduhelper/__init__.py
eduhelper/grades.py
eduhelper/studyplan.py
eduhelper/timeutils.py
eduhelper-1.0.0.dist-info/METADATA
eduhelper-1.0.0.dist-info/WHEEL
eduhelper-1.0.0.dist-info/top_level.txt
eduhelper-1.0.0.dist-info/RECORD
