Metadata-Version: 2.4
Name: eduhelper
Version: 1.0.0
Summary: A beginner-friendly Python library for student grades, deadlines, and study planning
Author: Mani Eyvazi
Author-email: manieyvazi83@yandex.ru
Classifier: Programming Language :: Python :: 3
Classifier: License :: OSI Approved :: MIT License
Classifier: Operating System :: OS Independent
Requires-Python: >=3.7
Dynamic: author
Dynamic: author-email
Dynamic: classifier
Dynamic: description
Dynamic: description-content-type
Dynamic: requires-python
Dynamic: summary
